pg_atlas/__init__.py
pg_atlas-0.0.1.dist-info/LICENSE
pg_atlas-0.0.1.dist-info/METADATA
pg_atlas-0.0.1.dist-info/WHEEL
pg_atlas-0.0.1.dist-info/top_level.txt
pg_atlas-0.0.1.dist-info/RECORD
