Metadata-Version: 2.1
Name: pg-atlas
Version: 0.0.1
Summary: Simple Image Atlas creator for Pygame framework
Home-page: https://github.com/damaskes/pg-atlas
Author: Ishkhan Verdyan
Author-email: vermasstud@gmail.com
License: UNKNOWN
Platform: UNKNOWN
Classifier: Programming Language :: Python :: 3
Classifier: License :: OSI Approved :: MIT License
Classifier: Operating System :: OS Independent
Requires-Python: >=3.6
